pyqwikswitch/__init__.py
pyqwikswitch/py.typed
pyqwikswitch/qsusb.py
pyqwikswitch/qwikswitch.py
pyqwikswitch-1.0.0.dist-info/WHEEL
pyqwikswitch-1.0.0.dist-info/METADATA
pyqwikswitch-1.0.0.dist-info/RECORD
