Metadata-Version: 2.3
Name: pyqwikswitch
Version: 1.0.0
Summary: Library to interface Qwikswitch USB Hub
Keywords: asyncio,qwikswitch
Author: Johann Kellerman
Author-email: Johann Kellerman <kellerza@gmail.com>
License: The MIT License (MIT)
Classifier: Programming Language :: Python :: 3 :: Only
Classifier: Programming Language :: Python :: 3.12
Classifier: Programming Language :: Python :: 3.13
Classifier: Programming Language :: Python :: 3.14
Requires-Dist: aiohttp>=3.12.15
Requires-Dist: attrs>=25.3
Requires-Python: >=3.12
